[
  {
    "inter": {
      "time": "2016-05-11T17:37:53.457448868305Z",
      "lat": 28.53081011,
      "fixFrac": 13.691489773661802,
      "lng": -81.84344805,
      "alt": 55.91
    },
    "cross": {
      "inZone": [
        true,
        false
      ],
      "crossingPair": [
        {
          "time": "2016-05-11T17:37:50Z",
          "lat": 28.53068333,
          "fix": 13,
          "lng": -81.84396667,
          "alt": 49
        },
        {
          "time": "2016-05-11T17:37:55Z",
          "lat": 28.53086667,
          "fix": 14,
          "lng": -81.84321667,
          "alt": 59
        }
      ]
    }
  },
  {
    "inter": {
      "time": "2016-05-11T18:42:02.2066183985Z",
      "lat": 28.56988915,
      "fixFrac": 768.6413236797009,
      "lng": -81.87599144,
      "alt": 1399.59
    },
    "cross": {
      "inZone": [
        true,
        false
      ],
      "crossingPair": [
        {
          "time": "2016-05-11T18:41:59Z",
          "lat": 28.56933333,
          "fix": 768,
          "lng": -81.87591667,
          "alt": 1406
        },
        {
          "time": "2016-05-11T18:42:04Z",
          "lat": 28.5702,
          "fix": 769,
          "lng": -81.87603333,
          "alt": 1396
        }
      ]
    }
  },
  {
    "inter": {
      "time": "2016-05-11T19:05:02.796717396892Z",
      "lat": 28.71159945,
      "fixFrac": 1039.8983586984464,
      "lng": -81.89630481,
      "alt": 1039.1
    },
    "cross": {
      "inZone": [
        false,
        true
      ],
      "crossingPair": [
        {
          "time": "2016-05-11T19:05:01Z",
          "lat": 28.7113,
          "fix": 1039,
          "lng": -81.8962,
          "alt": 1040
        },
        {
          "time": "2016-05-11T19:05:03Z",
          "lat": 28.71163333,
          "fix": 1040,
          "lng": -81.89631667,
          "alt": 1039
        }
      ]
    }
  },
  {
    "inter": {
      "time": "2016-05-11T20:37:30.032301665346Z",
      "lat": 28.25992204,
      "fixFrac": 2126.5161508326732,
      "lng": -81.82873655,
      "alt": 941.97
    },
    "cross": {
      "inZone": [
        false,
        true
      ],
      "crossingPair": [
        {
          "time": "2016-05-11T20:37:29Z",
          "lat": 28.26001667,
          "fix": 2126,
          "lng": -81.8289,
          "alt": 943
        },
        {
          "time": "2016-05-11T20:37:31Z",
          "lat": 28.25983333,
          "fix": 2127,
          "lng": -81.82858333,
          "alt": 941
        }
      ]
    }
  },
  null
]
