[
  {
    "inter": {
      "time": "2016-05-11T17:24:08.60488194747Z",
      "lat": 28.53002984,
      "fixFrac": 11.460488194747292,
      "lng": -81.84441081
    },
    "cross": {
      "inZone": [
        true,
        false
      ],
      "crossingPair": [
        {
          "time": "2016-05-11T17:24:04Z",
          "lat": 28.53018333,
          "fix": 11,
          "lng": -81.84521667
        },
        {
          "time": "2016-05-11T17:24:14Z",
          "lat": 28.52985,
          "fix": 12,
          "lng": -81.84346667
        }
      ]
    }
  },
  {
    "inter": {
      "time": "2016-05-11T18:30:38.683207343277Z",
      "lat": 28.56634117,
      "fixFrac": 403.33483703120726,
      "lng": -81.88105575
    },
    "cross": {
      "inZone": [
        true,
        false
      ],
      "crossingPair": [
        {
          "time": "2016-05-11T18:30:35Z",
          "lat": 28.56583333,
          "fix": 403,
          "lng": -81.88101667
        },
        {
          "time": "2016-05-11T18:30:46Z",
          "lat": 28.56735,
          "fix": 404,
          "lng": -81.88113333
        }
      ]
    }
  },
  {
    "inter": {
      "time": "2016-05-11T19:04:34.546490885784Z",
      "lat": 28.71158575,
      "fixFrac": 603.8866227214463,
      "lng": -81.89686856
    },
    "cross": {
      "inZone": [
        false,
        true
      ],
      "crossingPair": [
        {
          "time": "2016-05-11T19:04:31Z",
          "lat": 28.71108333,
          "fix": 603,
          "lng": -81.89688333
        },
        {
          "time": "2016-05-11T19:04:35Z",
          "lat": 28.71165,
          "fix": 604,
          "lng": -81.89686667
        }
      ]
    }
  },
  {
    "inter": {
      "time": "2016-05-11T20:51:17.632423941108Z",
      "lat": 28.25731802,
      "fixFrac": 1232.908105985277,
      "lng": -81.82886892
    },
    "cross": {
      "inZone": [
        false,
        true
      ],
      "crossingPair": [
        {
          "time": "2016-05-11T20:51:14Z",
          "lat": 28.25716667,
          "fix": 1232,
          "lng": -81.82955
        },
        {
          "time": "2016-05-11T20:51:18Z",
          "lat": 28.25733333,
          "fix": 1233,
          "lng": -81.8288
        }
      ]
    }
  },
  null
]
