[
  {
    "inter": {
      "time": "2016-05-09T18:10:34.278607050936Z",
      "lat": 28.52973416,
      "fixFrac": 11.426202350312055,
      "lng": -81.84502924
    },
    "cross": {
      "inZone": [
        true,
        false
      ],
      "crossingPair": [
        {
          "time": "2016-05-09T18:10:33Z",
          "lat": 28.52988333,
          "fix": 11,
          "lng": -81.84515
        },
        {
          "time": "2016-05-09T18:10:36Z",
          "lat": 28.52953333,
          "fix": 12,
          "lng": -81.84486667
        }
      ]
    }
  },
  {
    "inter": {
      "time": "2016-05-09T18:28:44.208533942679Z",
      "lat": 28.56436901,
      "fixFrac": 366.7361779808938,
      "lng": -81.88337964
    },
    "cross": {
      "inZone": [
        true,
        false
      ],
      "crossingPair": [
        {
          "time": "2016-05-09T18:28:42Z",
          "lat": 28.56405,
          "fix": 366,
          "lng": -81.88318333
        },
        {
          "time": "2016-05-09T18:28:45Z",
          "lat": 28.56448333,
          "fix": 367,
          "lng": -81.88345
        }
      ]
    }
  },
  null,
  null,
  null
]
