[
  {
    "inter": {
      "time": "2016-05-10T17:22:42.3694850329Z",
      "lat": 28.52962812,
      "fixFrac": 11.273897006580526,
      "lng": -81.84533885
    },
    "cross": {
      "inZone": [
        true,
        false
      ],
      "crossingPair": [
        {
          "time": "2016-05-10T17:22:41Z",
          "lat": 28.52978333,
          "fix": 11,
          "lng": -81.84546667
        },
        {
          "time": "2016-05-10T17:22:46Z",
          "lat": 28.52921667,
          "fix": 12,
          "lng": -81.845
        }
      ]
    }
  },
  {
    "inter": {
      "time": "2016-05-10T18:00:40.505234615275Z",
      "lat": 28.54828859,
      "fixFrac": 460.10104692305583,
      "lng": -81.89481921
    },
    "cross": {
      "inZone": [
        true,
        false
      ],
      "crossingPair": [
        {
          "time": "2016-05-10T18:00:40Z",
          "lat": 28.54826667,
          "fix": 460,
          "lng": -81.89473333
        },
        {
          "time": "2016-05-10T18:00:45Z",
          "lat": 28.54848333,
          "fix": 461,
          "lng": -81.89558333
        }
      ]
    }
  },
  {
    "inter": {
      "time": "2016-05-10T19:06:06.420511733476Z",
      "lat": 28.64273562,
      "fixFrac": 1239.8068372444925,
      "lng": -82.21642709
    },
    "cross": {
      "inZone": [
        false,
        true
      ],
      "crossingPair": [
        {
          "time": "2016-05-10T19:06:04Z",
          "lat": 28.64246667,
          "fix": 1239,
          "lng": -82.21598333
        },
        {
          "time": "2016-05-10T19:06:07Z",
          "lat": 28.6428,
          "fix": 1240,
          "lng": -82.21653333
        }
      ]
    }
  },
  null,
  null
]
